classifai/__init__.py
classifai/classifai.py
classifai-0.1.1.dist-info/LICENSE
classifai-0.1.1.dist-info/METADATA
classifai-0.1.1.dist-info/WHEEL
classifai-0.1.1.dist-info/entry_points.txt
classifai-0.1.1.dist-info/top_level.txt
classifai-0.1.1.dist-info/RECORD
