Metadata-Version: 2.1
Name: classifai
Version: 0.1.1
Summary: A command-line tool for AI-powered classification tasks using LLMs
Home-page: https://github.com/irthomasthomas/classifai
Author: Thomas Thomas
Author-email: irthomasthomas@Gmail.com
Classifier: Programming Language :: Python :: 3
Classifier: License :: OSI Approved :: MIT License
Classifier: Operating System :: OS Independent
Requires-Python: >=3.6
License-File: LICENSE
Requires-Dist: openai
